{
    "version": "2.2",
    "updated": "2025-3-28T00:00:00Z",
    "authCodes": [
        {
            "key": "AUTH-2025",
            "created": "2025-3-28",
            "expire": "2025-5-01",
            "maxDevices": 2,
            "devices": [
                "kcl-v6-a6c365f796408d35"
            ],
            "owner": "管理员",
            "notes": "管理员授权"
        },
        {
            "key": "KCL-2025",
            "created": "2025-3-28",
            "expire": "2025-5-01",
            "maxDevices": 2,
            "devices": [
                "kcl-v6-97763d75fcf77"
            ],
            "owner": "VIP用户",
            "notes": "天数授权"
        },
        {
            "key": "KCL-2025-01",
            "created": "2025-3-31",
            "expire": "2025-6-1",
            "maxDevices": 2,
            "devices": [
                "kcl-v6-457ee7d9a1071e5b"
            ],
            "owner": "VIP用户",
            "notes": "天数授权"
        },
        {
            "key": "KCL-2025-02",
            "created": "2025-3-31",
            "expire": "2025-6-1",
            "maxDevices": 2,
            "devices": [
                "kcl-v6-8c831b1ef55f1fbc"
            ],
            "owner": "VIP用户",
            "notes": "天数授权"
        },
        {
            "key": "KCL-2025-03",
            "created": "2025-3-31",
            "expire": "2025-6-1",
            "maxDevices": 2,
            "devices": [
                "kcl-v6-f0a48ec6bad45804"
            ],
            "owner": "VIP用户",
            "notes": "天数授权"
        },
        {
            "key": "KCL-2025-04",
            "created": "2025-3-31",
            "expire": "2025-6-1",
            "maxDevices": 2,
            "devices": [
                "kcl-v6-381b94edde348ecf"
            ],
            "owner": "VIP用户",
            "notes": "天数授权"
        }
    ]
}
